MANIFEST.in
README.md
setup.cfg
setup.py
bca4abm/__init__.py
bca4abm/bca4abm.py
bca4abm/defaults.py
bca4abm.egg-info/PKG-INFO
bca4abm.egg-info/SOURCES.txt
bca4abm.egg-info/dependency_links.txt
bca4abm.egg-info/entry_points.txt
bca4abm.egg-info/requires.txt
bca4abm.egg-info/top_level.txt
bca4abm/cli/__init__.py
bca4abm/cli/main.py
bca4abm/examples/example_4step/configs/aggregate_demographics.csv
bca4abm/examples/example_4step/configs/aggregate_demographics.yaml
bca4abm/examples/example_4step/configs/aggregate_od.yaml
bca4abm/examples/example_4step/configs/aggregate_od_revised.csv
bca4abm/examples/example_4step/configs/aggregate_zone.csv
bca4abm/examples/example_4step/configs/aggregate_zone.yaml
bca4abm/examples/example_4step/configs/link_daily.csv
bca4abm/examples/example_4step/configs/link_daily.yaml
bca4abm/examples/example_4step/configs/logging.yaml
bca4abm/examples/example_4step/configs/settings.yaml
bca4abm/examples/example_4step/configs/tables.yaml
bca4abm/examples/example_4step/data/moves_2010_summer_running_rates.csv
bca4abm/examples/example_4step/data/zone_districts.csv
bca4abm/examples/example_4step/data/base-data/cocs.csv
bca4abm/examples/example_4step/data/base-data/mce_input_cval.csv
bca4abm/examples/example_4step/data/base-data/mce_input_links_0001.csv
bca4abm/examples/example_4step/data/base-data/mce_input_links_0102.csv
bca4abm/examples/example_4step/data/base-data/mce_input_links_0203.csv
bca4abm/examples/example_4step/data/base-data/mce_input_links_0304.csv
bca4abm/examples/example_4step/data/base-data/mce_input_links_0405.csv
bca4abm/examples/example_4step/data/base-data/mce_input_links_0506.csv
bca4abm/examples/example_4step/data/base-data/mce_input_links_0607.csv
bca4abm/examples/example_4step/data/base-data/mce_input_links_0708.csv
bca4abm/examples/example_4step/data/base-data/mce_input_links_0809.csv
bca4abm/examples/example_4step/data/base-data/mce_input_links_0910.csv
bca4abm/examples/example_4step/data/base-data/mce_input_links_1011.csv
bca4abm/examples/example_4step/data/base-data/mce_input_links_1112.csv
bca4abm/examples/example_4step/data/base-data/mce_input_links_1213.csv
