Metadata-Version: 1.0
Name: bca4abm
Version: 0.6
Summary: Benefit Calculations for Travel Models
Home-page: https://github.com/RSGInc/bca4abm
Author: contributing authors
Author-email: ben.stabler@rsginc.com
License: BSD-3
Platform: UNKNOWN
